edr-accessor/__init__.py
edr_accessor/__init__.py
edr_accessor-0.1.7.dist-info/LICENSE
edr_accessor-0.1.7.dist-info/METADATA
edr_accessor-0.1.7.dist-info/WHEEL
edr_accessor-0.1.7.dist-info/top_level.txt
edr_accessor-0.1.7.dist-info/RECORD
