Metadata-Version: 2.1
Name: edr-accessor
Version: 0.1.7
Summary: A pandas DataFrame accessor for accessing Enterprise Data Repository (EDR) tables with Spark.
Author: Peter Boyd
Author-email: peter.g.boyd@gmail.com
License: MIT
Classifier: Development Status :: 3 - Alpha
Classifier: Intended Audience :: Developers
Classifier: Natural Language :: English
Classifier: Programming Language :: Python :: 3
Classifier: Operating System :: OS Independent
License-File: LICENSE
Requires-Dist: pandas
Requires-Dist: pyspark
